CHANGES.txt
README.txt
bootstrap.py
buildout.cfg
setup.py
src/zope/__init__.py
src/zope.rdb.egg-info/PKG-INFO
src/zope.rdb.egg-info/SOURCES.txt
src/zope.rdb.egg-info/dependency_links.txt
src/zope.rdb.egg-info/namespace_packages.txt
src/zope.rdb.egg-info/not-zip-safe
src/zope.rdb.egg-info/requires.txt
src/zope.rdb.egg-info/top_level.txt
src/zope/rdb/DEPENDENCIES.cfg
src/zope/rdb/SETUP.cfg
src/zope/rdb/__init__.py
src/zope/rdb/configure.zcml
src/zope/rdb/gadflyda.py
src/zope/rdb/gadflyda.zcml
src/zope/rdb/gadflyzcml.py
src/zope/rdb/interfaces.py
src/zope/rdb/meta.zcml
src/zope/rdb/rdb-configure.zcml
src/zope/rdb/rdb-meta.zcml
src/zope/rdb/zcml.py
src/zope/rdb/browser/__init__.py
src/zope/rdb/browser/configure.zcml
src/zope/rdb/browser/gadflyda.zcml
src/zope/rdb/browser/rdb.py
src/zope/rdb/browser/rdbconnection.pt
src/zope/rdb/browser/rdbtestresults.pt
src/zope/rdb/browser/rdbtestsql.pt
src/zope/rdb/gadfly/COPYRIGHT
src/zope/rdb/gadfly/DLispShort.py
src/zope/rdb/gadfly/DumbLispGen.py
src/zope/rdb/gadfly/SQLTESTG.py
src/zope/rdb/gadfly/__init__.py
src/zope/rdb/gadfly/gadfly.html
src/zope/rdb/gadfly/gadfly.py
src/zope/rdb/gadfly/gfSQL.html
src/zope/rdb/gadfly/gfclient.py
src/zope/rdb/gadfly/gfdb0.py
src/zope/rdb/gadfly/gffaq.html
src/zope/rdb/gadfly/gfinstall.py
src/zope/rdb/gadfly/gfintrospect.py
src/zope/rdb/gadfly/gfrecover.html
src/zope/rdb/gadfly/gfserve.py
src/zope/rdb/gadfly/gfsocket.py
src/zope/rdb/gadfly/gfstest.py
src/zope/rdb/gadfly/gftest.py
src/zope/rdb/gadfly/idl.py
src/zope/rdb/gadfly/index.html
src/zope/rdb/gadfly/kjParseBuild.py
src/zope/rdb/gadfly/kjParser.py
src/zope/rdb/gadfly/kjSet.py
src/zope/rdb/gadfly/kjbuckets0.py
src/zope/rdb/gadfly/kjpylint.py
src/zope/rdb/gadfly/kwParsing.html
src/zope/rdb/gadfly/pygram.py
src/zope/rdb/gadfly/relalg.py
src/zope/rdb/gadfly/remotetest.py
src/zope/rdb/gadfly/server.html
src/zope/rdb/gadfly/sql.mar
src/zope/rdb/gadfly/sqlbind.py
src/zope/rdb/gadfly/sqlgen.py
src/zope/rdb/gadfly/sqlgram.py
src/zope/rdb/gadfly/sqlgtest.py
src/zope/rdb/gadfly/sqlmod.py
src/zope/rdb/gadfly/sqlsem.py
src/zope/rdb/gadfly/sqlwhere.py
src/zope/rdb/tests/__init__.py
src/zope/rdb/tests/gadflyroot.zcml
src/zope/rdb/tests/rdb.zcml
src/zope/rdb/tests/stubs.py
src/zope/rdb/tests/test_directives.py
